quantstream/__init__.py
quantstream/__main__.py
quantstream/config.py
quantstream/datasets/__init__.py
quantstream/datasets/findataset.py
quantstream/datasets/market.py
quantstream/datasets/portfolio.py
quantstream/decorators/__init__.py
quantstream/decorators/api_validation.py
quantstream/modules/__init__.py
quantstream/modules/comodities.py
quantstream/modules/economics.py
quantstream/modules/fundamentals.py
quantstream/modules/option_chain.py
quantstream/modules/timeseries.py
quantstream/tests/test_fundamentals.py
quantstream/tests/test_timeseries.py
quantstream/utils/__init__.py
quantstream/utils/returns.py
quantstream-0.0.4.dist-info/METADATA
quantstream-0.0.4.dist-info/WHEEL
quantstream-0.0.4.dist-info/entry_points.txt
quantstream-0.0.4.dist-info/licenses/LICENSE
quantstream-0.0.4.dist-info/RECORD
