Metadata-Version: 2.4
Name: quantstream
Version: 0.0.4
Summary: 'QuantStream' is a Python library for financial data analysis and visualization.
Author: quantstream
License: The MIT License (MIT)
License-File: LICENSE
Classifier: Development Status :: 3 - Alpha
Classifier: Intended Audience :: Developers
Classifier: License :: OSI Approved :: MIT License
Classifier: Operating System :: OS Independent
Classifier: Programming Language :: Python :: 3
Classifier: Programming Language :: Python :: 3.11
Classifier: Topic :: Software Development :: Libraries :: Python Modules
Requires-Python: >=3.11
Requires-Dist: fmpsdk>=20240330.0
Requires-Dist: matplotlib>=3.8.4
Requires-Dist: mplfinance>=0.12.10b0
Requires-Dist: nbformat>=5.10.4
Requires-Dist: numpy>=1.26.4
Requires-Dist: numpydoc-validation>=0.1.0
Requires-Dist: pandas>=2.2.1
Requires-Dist: plotly>=5.22.0
Requires-Dist: polars>=0.20.25
Requires-Dist: pypdf>=4.2.0
Requires-Dist: pytest>=8.2.2
Requires-Dist: python-dotenv>=1.0.1
Requires-Dist: pyyaml>=6.0
Requires-Dist: requests>=2.26.0
Requires-Dist: rich>=13.7.1
Requires-Dist: typer[all]>=0.9.0
Requires-Dist: voila>=0.5.7
Requires-Dist: xarray>=2024.2.0
Provides-Extra: dev
Requires-Dist: bandit>=1.7.1; extra == 'dev'
Requires-Dist: black>=24.3.0; extra == 'dev'
Requires-Dist: click>=8.1.7; extra == 'dev'
Requires-Dist: coverage-badge>=1.1.0; extra == 'dev'
Requires-Dist: coverage>=7.4.4; extra == 'dev'
Requires-Dist: darglint>=1.8.1; extra == 'dev'
Requires-Dist: ipykernel>=6.29.4; extra == 'dev'
Requires-Dist: isort[colors]>=5.10.1; extra == 'dev'
Requires-Dist: mkdocs-material>=9.5.34; extra == 'dev'
Requires-Dist: mkdocs>=1.6.1; extra == 'dev'
Requires-Dist: mkdocstrings[python]>=0.26.1; extra == 'dev'
Requires-Dist: mypy-extensions>=1.0.0; extra == 'dev'
Requires-Dist: mypy>=1.0; extra == 'dev'
Requires-Dist: pre-commit>=3.6.2; extra == 'dev'
Requires-Dist: pydocstyle>=6.1.1; extra == 'dev'
Requires-Dist: pylint>=3.1.0; extra == 'dev'
Requires-Dist: pytest-cov>=4.1.0; extra == 'dev'
Requires-Dist: pytest-html>=4.1.1; extra == 'dev'
Requires-Dist: pytest>=8.1.1; extra == 'dev'
Requires-Dist: pyupgrade>=3.15.1; extra == 'dev'
Requires-Dist: requests-mock>=1.11.0; extra == 'dev'
Requires-Dist: ruff>=0.0.276; extra == 'dev'
